celescope/__init__.py
celescope/celescope.py
celescope/chemistry_dict.py
celescope/bulk_rna/__init__.py
celescope/bulk_rna/multi_bulk_rna.py
celescope/bulk_rna/split.py
celescope/bulk_rna/starsolo.py
celescope/bulk_vdj/__init__.py
celescope/bulk_vdj/consensus.py
celescope/bulk_vdj/mapping_vdj.py
celescope/bulk_vdj/multi_bulk_vdj.py
celescope/capture_virus/__init__.py
celescope/capture_virus/analysis_virus.py
celescope/capture_virus/count.py
celescope/capture_virus/count_virus.py
celescope/capture_virus/featureCounts.py
celescope/capture_virus/filter_virus.py
celescope/capture_virus/mkref.py
celescope/capture_virus/multi_capture_virus.py
celescope/capture_virus/star_virus.py
celescope/citeseq/__init__.py
celescope/citeseq/analysis_cite.py
celescope/citeseq/count_cite.py
celescope/citeseq/mapping_tag.py
celescope/citeseq/multi_citeseq.py
celescope/data/__init__.py
celescope/data/Clindex/tag_barcode.fasta
celescope/data/Clindex/tag_linker.fasta
celescope/data/HLA/hla_reference_rna.fasta
celescope/data/chemistry/__init__.py
celescope/data/chemistry/GEXSCOPE-V1/bc.txt
celescope/data/chemistry/GEXSCOPE-V1/linker1.txt
celescope/data/chemistry/GEXSCOPE-V1/linker2.txt
celescope/data/chemistry/GEXSCOPE-V2/bc1.txt
celescope/data/chemistry/GEXSCOPE-V2/bc2.txt
celescope/data/chemistry/GEXSCOPE-V2/bc3.txt
celescope/data/chemistry/GEXSCOPE-V2/linker1.txt
celescope/data/chemistry/GEXSCOPE-V2/linker2.txt
celescope/data/chemistry/GEXSCOPE-V3/bc1.txt
celescope/data/chemistry/GEXSCOPE-V3/bc2.txt
celescope/data/chemistry/GEXSCOPE-V3/bc3.txt
celescope/data/chemistry/GEXSCOPE-V3/linker1.txt
celescope/data/chemistry/GEXSCOPE-V3/linker2.txt
celescope/data/chemistry/bulk_rna-V1/bc.txt
celescope/data/chemistry/bulk_rna-V2/bc.txt
celescope/data/chemistry/bulk_rna-V3/bc.txt
celescope/data/chemistry/bulk_rna-bulk_vdj_match/bc.txt
celescope/data/chemistry/bulk_vdj/bc.txt
celescope/data/chemistry/bulk_vdj/linker.txt
celescope/data/chemistry/flv/bc.txt
celescope/data/chemistry/flv/linker1.txt
celescope-2.11.0.dist-info/licenses/LICENSE
celescope-2.11.0.dist-info/METADATA
celescope-2.11.0.dist-info/WHEEL
celescope-2.11.0.dist-info/entry_points.txt
celescope-2.11.0.dist-info/top_level.txt
celescope-2.11.0.dist-info/RECORD
