Metadata-Version: 2.4
Name: celescope
Version: 2.11.0
Summary: Single Cell Analysis Pipelines
Home-page: https://github.com/singleron-RD/CeleScope
Author: zhouyiqi
Author-email: zhouyiqi@singleronbio.com
Classifier: Programming Language :: Python :: 3
Classifier: License :: OSI Approved :: MIT License
Classifier: Operating System :: OS Independent
Requires-Python: >=3.6
License-File: LICENSE
Requires-Dist: cutadapt==3.7
Requires-Dist: pysam>=0.18.0
Requires-Dist: scipy==1.13.1
Requires-Dist: numpy==1.26.0
Requires-Dist: jinja2>=2.10
Requires-Dist: xopen>=1.1
Requires-Dist: scikit-learn==1.2.2
Requires-Dist: plotly==5.24.1
Requires-Dist: plotnine==0.9.0
Requires-Dist: matplotlib==3.5.3
Requires-Dist: cython
Requires-Dist: pytest
Requires-Dist: scanpy==1.9.3
Requires-Dist: statsmodels
Requires-Dist: leidenalg
Requires-Dist: igraph
Requires-Dist: pandas==1.4.2
Requires-Dist: biopython
Requires-Dist: anndata==0.7.6
Requires-Dist: kaleido
Requires-Dist: pyarrow
Dynamic: author
Dynamic: author-email
Dynamic: classifier
Dynamic: description
Dynamic: description-content-type
Dynamic: home-page
Dynamic: license-file
Dynamic: requires-dist
Dynamic: requires-python
Dynamic: summary
